{
  "Title": "\u7b97\u4f8b2\uff1a\u4e8c\u7ef4\u4e24\u6746\u6841\u67b6\u7ed3\u6784",
  "nsd": 2,
  "ndof": 2,
  "nnp": 3,
  "nel": 2,
  "nen": 2,
  "X": [
    [
      1.0,
      0.0
    ],
    [
      0.0,
      0.0
    ],
    [
      1.0,
      1.0
    ]
  ],
  "IEN": [
    [
      1,
      3
    ],
    [
      2,
      3
    ]
  ],
  "E": [
    1.0,
    1.0
  ],
  "A": [
    1.0,
    1.0
  ],
  "displacement_bc": [
    {
      "node": 1,
      "dofs": [
        1,
        2
      ],
      "values": [
        0.0,
        0.0
      ]
    },
    {
      "node": 2,
      "dofs": [
        1,
        2
      ],
      "values": [
        0.0,
        0.0
      ]
    }
  ],
  "nodal_loads": [
    {
      "node": 3,
      "forces": [
        10.0,
        0.0
      ]
    }
  ],
  "expected_results": {
    "node3_displacement": [
      38.284271,
      -10.0
    ],
    "stress_unit1": -10.0,
    "stress_unit2": 14.142136
  }
}